{"docs_components_alert.md":"AO2QXxj4","docs_components_avatar.md":"D78Q_g26","docs_components_badge.md":"B3FcAGsj","docs_components_breadcrumbs.md":"PD2wRafB","docs_components_button.md":"KHnxr4Ao","docs_components_calendar.md":"BZ8cjMC7","docs_components_charts.md":"DeB1-bQ1","docs_components_checkbox.md":"BGWfRayf","docs_components_circularprogressbar.md":"Bv_6G2zE","docs_components_combobox.md":"CGGXwOv-","docs_components_datepicker.md":"DKJFjC--","docs_components_dialog.md":"BFoTUbqV","docs_components_divider.md":"gZpNdma9","docs_components_dropdown.md":"G75MQpIU","docs_components_errormessage.md":"BGsVovlS","docs_components_fileuploader.md":"BK3EDR8M","docs_components_formcontrol.md":"_jMfT629","docs_components_itemlistrow.md":"BAljifwW","docs_components_legacy.md":"B8UZ83iN","docs_components_listview.md":"BGdbsJqh","docs_components_monthpicker.md":"DZsJCCrH","docs_components_multiselect.md":"DvKWhT9g","docs_components_password.md":"B75eG5FA","docs_components_popover.md":"CB9XMiuB","docs_components_progress.md":"D2qXBNwY","docs_components_rating.md":"BTkmP3CS","docs_components_select.md":"B2o54QHR","docs_components_sidebar.md":"Cms8nfHt","docs_components_slider.md":"Cgl0LkKx","docs_components_switch.md":"Ts5Eru72","docs_components_tabs.md":"DWjNWyea","docs_components_textarea.md":"DjfHZh25","docs_components_texteditor.md":"ChQWMDZv","docs_components_textinput.md":"D9pY0KKz","docs_components_timepicker.md":"BvM_ylFM","docs_components_toast.md":"wGi6oglt","docs_components_tooltip.md":"B32GzMwe","docs_components_tree.md":"BUgExTh1","docs_data-fetching_document-resource.md":"BqF-XTH_","docs_data-fetching_list-resource.md":"Cul_ZRGy","docs_data-fetching_resource.md":"BL7j2QfN","docs_design-system_background-color.md":"7zojF-gQ","docs_design-system_border-color.md":"DhDG8Onq","docs_design-system_border-radius.md":"Dg-F3wc3","docs_design-system_drop-shadow.md":"CRPIJDDe","docs_design-system_text-color.md":"1u9EC6Qj","docs_design-system_text.md":"EVUIgEgu","docs_getting-started.md":"ElxKltuv","docs_introduction.md":"Bgc1amSU","docs_other_directives.md":"CuMoruQw","docs_other_icons.md":"CMddiRGm","docs_other_utilities.md":"Cs6nXNoO","index.md":"rbBnK2jm"}
